LICENSE.md
MANIFEST.in
README.md
setup.py
minvime/__init__.py
minvime/__main__.py
minvime/estimator_classification.py
minvime/estimator_regression.py
minvime/generator.py
minvime/minvime.py
minvime.egg-info/PKG-INFO
minvime.egg-info/SOURCES.txt
minvime.egg-info/dependency_links.txt
minvime.egg-info/entry_points.txt
minvime.egg-info/requires.txt
minvime.egg-info/top_level.txt
minvime/static/logo.png
minvime/static/logo.xcf
minvime/static/logo_small.png
minvime/static/logo_small.xcf
minvime/templates/about.html
minvime/templates/analyse.html
minvime/templates/analyse_intervention.html
minvime/templates/analyse_proportional.html
minvime/templates/analyse_thresholded.html
minvime/templates/config_form.html
minvime/templates/error.html
minvime/templates/footer.html
minvime/templates/header.html
minvime/templates/index.html
minvime/templates/intervention.html
minvime/templates/intervention_form.html
minvime/templates/payoff_matrix.html
minvime/templates/proportional.html
minvime/templates/proportional_form.html
minvime/templates/thresholded.html
minvime/templates/thresholded_form.html
minvime/uploads/README.md