Metadata-Version: 2.1
Name: minvime
Version: 1.0.3
Summary: Python Application for Estimating Minimum Viable Model Performance.
Home-page: http://getting-data-science-done.com
Author: John Hawkins
Author-email: john@getting-data-science-done.com
License: MIT
Project-URL: Documentation, https://minvime.readthedocs.io
Project-URL: Source, https://github.com/john-hawkins/minvime
Project-URL: Tracker, https://github.com/john-hawkins/minvime/issues
License-File: LICENSE.md
